BashGame/__init__.py
BashGame/main.py
bashgame-1.0.1.dist-info/licenses/LICENSE
bashgame-1.0.1.dist-info/METADATA
bashgame-1.0.1.dist-info/WHEEL
bashgame-1.0.1.dist-info/top_level.txt
bashgame-1.0.1.dist-info/RECORD
