Metadata-Version: 2.4
Name: BashGame
Version: 1.0.1
Summary: A Module for create a Game in terminal
Author-email: Grivy16 <grivy16public@gmail.com>
License: Apache
Project-URL: Homepage, https://github.com/Grivy16/BashGame
Requires-Python: >=3.8
License-File: LICENSE
Dynamic: license-file
